{
	"credit": "Made with Blockbench",
	"texture_size": [64, 64],
	"textures": {
		"2": "scorchedguns:item/auto_crossbow",
		"particle": "scorchedguns:item/auto_crossbow"
	},
	"elements": [
		{
			"from": [6.75, 1.3, 11.75],
			"to": [9.25, 4.3, 16.25],
			"rotation": {"angle": 0, "axis": "y", "origin": [0, -0.5, 0]},
			"faces": {
				"north": {"uv": [2.5, 2.5, 3.125, 3.25], "texture": "#2"},
				"east": {"uv": [5.5, 3, 6.625, 3.75], "texture": "#2"},
				"south": {"uv": [3, 0, 3.625, 0.75], "texture": "#2"},
				"west": {"uv": [0, 5.75, 1.125, 6.5], "texture": "#2"},
				"up": {"uv": [2.625, 6.875, 2, 5.75], "texture": "#2"},
				"down": {"uv": [6.375, 5.25, 5.75, 6.375], "texture": "#2"}
			}
		},
		{
			"from": [7, 2.3, 3.5],
			"to": [9, 4.3, 11.5],
			"rotation": {"angle": 0, "axis": "y", "origin": [0, -0.5, 0]},
			"faces": {
				"north": {"uv": [4.5, 3, 5, 3.5], "texture": "#2"},
				"east": {"uv": [5.25, 4.25, 7.25, 4.75], "texture": "#2"},
				"south": {"uv": [1, 5, 1.5, 5.5], "texture": "#2"},
				"west": {"uv": [5.25, 4.75, 7.25, 5.25], "texture": "#2"},
				"up": {"uv": [3.5, 6.75, 3, 4.75], "texture": "#2"},
				"down": {"uv": [5.75, 5.25, 5.25, 7.25], "texture": "#2"}
			}
		},
		{
			"from": [7.75, 4.3, 3.5],
			"to": [8.25, 5.3, 4.5],
			"rotation": {"angle": 0, "axis": "y", "origin": [0, -0.5, 0]},
			"faces": {
				"north": {"uv": [2.25, 5.5, 2.375, 5.75], "texture": "#2"},
				"east": {"uv": [1.5, 4.5, 1.75, 4.75], "texture": "#2"},
				"south": {"uv": [6.5, 6.25, 6.625, 6.5], "texture": "#2"},
				"west": {"uv": [5, 4.25, 5.25, 4.5], "texture": "#2"},
				"up": {"uv": [5.125, 7.75, 5, 7.5], "texture": "#2"},
				"down": {"uv": [2.375, 7.75, 2.25, 8], "texture": "#2"}
			}
		},
		{
			"from": [6.75, 1.8, 6.75],
			"to": [9.25, 3.8, 11.75],
			"rotation": {"angle": 0, "axis": "y", "origin": [0, -0.5, 0]},
			"faces": {
				"north": {"uv": [4, 3.75, 4.625, 4.25], "texture": "#2"},
				"east": {"uv": [1.75, 5, 3, 5.5], "texture": "#2"},
				"south": {"uv": [7, 5.75, 7.625, 6.25], "texture": "#2"},
				"west": {"uv": [5.75, 3.75, 7, 4.25], "texture": "#2"},
				"up": {"uv": [1.875, 7, 1.25, 5.75], "texture": "#2"},
				"down": {"uv": [6.375, 1.75, 5.75, 3], "texture": "#2"}
			}
		},
		{
			"from": [6.75, 2.05, 2],
			"to": [9.25, 4.55, 3.5],
			"rotation": {"angle": 0, "axis": "y", "origin": [0, -0.5, 0]},
			"faces": {
				"north": {"uv": [2.75, 6.75, 3.375, 7.375], "texture": "#2"},
				"east": {"uv": [0, 7.5, 0.375, 8.125], "texture": "#2"},
				"south": {"uv": [6.75, 3, 7.375, 3.625], "texture": "#2"},
				"west": {"uv": [7.5, 0, 7.875, 0.625], "texture": "#2"},
				"up": {"uv": [1.125, 7.875, 0.5, 7.5], "texture": "#2"},
				"down": {"uv": [8.125, 1.5, 7.5, 1.875], "texture": "#2"}
			}
		},
		{
			"from": [8.25, 3.8, 6.25],
			"to": [11.75, 4.8, 10.25],
			"rotation": {"angle": 0, "axis": "y", "origin": [0, -0.5, 0]},
			"faces": {
				"north": {"uv": [7.25, 7, 8.125, 7.25], "texture": "#2"},
				"east": {"uv": [7.25, 4.25, 8.25, 4.5], "texture": "#2"},
				"south": {"uv": [7.5, 0.75, 8.375, 1], "texture": "#2"},
				"west": {"uv": [7.25, 4.5, 8.25, 4.75], "texture": "#2"},
				"up": {"uv": [4.875, 5.25, 4, 4.25], "texture": "#2"},
				"down": {"uv": [4.875, 5.5, 4, 6.5], "texture": "#2"}
			}
		},
		{
			"from": [7, 3.55, 8],
			"to": [9, 3.8, 11.5],
			"rotation": {"angle": 0, "axis": "y", "origin": [0, -0.5, 0]},
			"faces": {
				"north": {"uv": [6, 1.5, 6.5, 1.625], "texture": "#2"},
				"east": {"uv": [7.5, 3.5, 8.375, 3.625], "texture": "#2"},
				"south": {"uv": [1.75, 7.75, 2.25, 7.875], "texture": "#2"},
				"west": {"uv": [4, 7.5, 4.875, 7.625], "texture": "#2"},
				"up": {"uv": [5, 7.375, 4.5, 6.5], "texture": "#2"},
				"down": {"uv": [7, 5.25, 6.5, 6.125], "texture": "#2"}
			}
		},
		{
			"from": [9.25, 2.8, 6.25],
			"to": [11.75, 3.8, 10.25],
			"rotation": {"angle": 0, "axis": "y", "origin": [0, -0.5, 0]},
			"faces": {
				"north": {"uv": [0, 5.5, 0.625, 5.75], "texture": "#2"},
				"east": {"uv": [7.25, 4.75, 8.25, 5], "texture": "#2"},
				"south": {"uv": [1.75, 7.5, 2.375, 7.75], "texture": "#2"},
				"west": {"uv": [7.25, 5, 8.25, 5.25], "texture": "#2"},
				"up": {"uv": [6.875, 1, 6.25, 0], "texture": "#2"},
				"down": {"uv": [0.625, 6.5, 0, 7.5], "texture": "#2"}
			}
		},
		{
			"from": [7, 1.3, 7],
			"to": [9, 1.8, 10.5],
			"rotation": {"angle": 0, "axis": "y", "origin": [0, -0.5, 0]},
			"faces": {
				"north": {"uv": [3.5, 7.75, 4, 7.875], "texture": "#2"},
				"east": {"uv": [5.75, 7.5, 6.625, 7.625], "texture": "#2"},
				"south": {"uv": [4, 7.75, 4.5, 7.875], "texture": "#2"},
				"west": {"uv": [6.75, 7.5, 7.625, 7.625], "texture": "#2"},
				"up": {"uv": [6.25, 7.375, 5.75, 6.5], "texture": "#2"},
				"down": {"uv": [6.75, 6.5, 6.25, 7.375], "texture": "#2"}
			}
		},
		{
			"from": [7.25, -1.7, 14.95],
			"to": [8.75, 2.3, 16.45],
			"rotation": {"angle": -22.5, "axis": "x", "origin": [8, 0.55, 15.7]},
			"faces": {
				"north": {"uv": [3.5, 6.75, 3.875, 7.75], "texture": "#2"},
				"east": {"uv": [6.75, 6.25, 7.125, 7.25], "texture": "#2"},
				"south": {"uv": [7, 0, 7.375, 1], "texture": "#2"},
				"west": {"uv": [1.25, 7, 1.625, 8], "texture": "#2"},
				"up": {"uv": [7.875, 2.375, 7.5, 2], "texture": "#2"},
				"down": {"uv": [2.875, 7.5, 2.5, 7.875], "texture": "#2"}
			}
		},
		{
			"from": [3.25, -1.2, 3.95],
			"to": [7.25, -0.7, 5.45],
			"rotation": {"angle": 22.5, "axis": "x", "origin": [8, 0.55, 15.7]},
			"faces": {
				"north": {"uv": [7.5, 2.5, 8.5, 2.625], "texture": "#2"},
				"east": {"uv": [4.5, 7.75, 4.875, 7.875], "texture": "#2"},
				"south": {"uv": [7.5, 2.75, 8.5, 2.875], "texture": "#2"},
				"west": {"uv": [5.5, 7.75, 5.875, 7.875], "texture": "#2"},
				"up": {"uv": [8, 1.375, 7, 1], "texture": "#2"},
				"down": {"uv": [2.75, 7, 1.75, 7.375], "texture": "#2"}
			}
		},
		{
			"from": [8.75, -1.2, 3.95],
			"to": [12.75, -0.7, 5.45],
			"rotation": {"angle": 22.5, "axis": "x", "origin": [8, 0.55, 15.7]},
			"faces": {
				"north": {"uv": [7.5, 3, 8.5, 3.125], "texture": "#2"},
				"east": {"uv": [7.75, 5.75, 8.125, 5.875], "texture": "#2"},
				"south": {"uv": [7.5, 3.25, 8.5, 3.375], "texture": "#2"},
				"west": {"uv": [6, 7.75, 6.375, 7.875], "texture": "#2"},
				"up": {"uv": [8, 4.125, 7, 3.75], "texture": "#2"},
				"down": {"uv": [8, 5.25, 7, 5.625], "texture": "#2"}
			}
		},
		{
			"from": [7.75, 0.8, 14.45],
			"to": [8.25, 1.3, 14.95],
			"rotation": {"angle": 0, "axis": "y", "origin": [0, -0.5, 0]},
			"faces": {
				"north": {"uv": [5, 7.75, 5.125, 7.875], "texture": "#2"},
				"east": {"uv": [7.75, 6, 7.875, 6.125], "texture": "#2"},
				"south": {"uv": [6.5, 7.75, 6.625, 7.875], "texture": "#2"},
				"west": {"uv": [6.75, 7.75, 6.875, 7.875], "texture": "#2"},
				"up": {"uv": [7.125, 7.875, 7, 7.75], "texture": "#2"},
				"down": {"uv": [7.375, 7.75, 7.25, 7.875], "texture": "#2"}
			}
		},
		{
			"from": [7.5, 0.75, 10.75],
			"to": [8.5, 4.75, 12.75],
			"rotation": {"angle": -22.5, "axis": "z", "origin": [8, 2.75, 11.75]},
			"faces": {
				"north": {"uv": [5, 5.5, 5.25, 6.5], "texture": "#2"},
				"east": {"uv": [1, 4, 1.5, 5], "texture": "#2"},
				"south": {"uv": [2.75, 5.75, 3, 6.75], "texture": "#2"},
				"west": {"uv": [3.5, 5.75, 4, 6.75], "texture": "#2"},
				"up": {"uv": [1.75, 4.5, 1.5, 4], "texture": "#2"},
				"down": {"uv": [5.75, 7.25, 5.5, 7.75], "texture": "#2"}
			}
		},
		{
			"from": [6, 2.25, 10.75],
			"to": [10, 3.25, 12.75],
			"rotation": {"angle": 22.5, "axis": "z", "origin": [8, 2.75, 11.75]},
			"faces": {
				"north": {"uv": [7.25, 6.25, 8.25, 6.5], "texture": "#2"},
				"east": {"uv": [4.5, 3.5, 5, 3.75], "texture": "#2"},
				"south": {"uv": [7.25, 6.5, 8.25, 6.75], "texture": "#2"},
				"west": {"uv": [2.5, 4.75, 3, 5], "texture": "#2"},
				"up": {"uv": [7, 1.5, 6, 1], "texture": "#2"},
				"down": {"uv": [7.5, 1.5, 6.5, 2], "texture": "#2"}
			}
		},
		{
			"from": [6, 2.25, 10.75],
			"to": [10, 3.25, 12.75],
			"rotation": {"angle": -22.5, "axis": "z", "origin": [8, 2.75, 11.75]},
			"faces": {
				"north": {"uv": [6.75, 7.25, 7.75, 7.5], "texture": "#2"},
				"east": {"uv": [0.5, 5.25, 1, 5.5], "texture": "#2"},
				"south": {"uv": [7.25, 6.75, 8.25, 7], "texture": "#2"},
				"west": {"uv": [5.75, 0, 6.25, 0.25], "texture": "#2"},
				"up": {"uv": [7.5, 2.5, 6.5, 2], "texture": "#2"},
				"down": {"uv": [7.5, 2.5, 6.5, 3], "texture": "#2"}
			}
		},
		{
			"from": [7.5, 0.75, 10.75],
			"to": [8.5, 4.75, 12.75],
			"rotation": {"angle": 22.5, "axis": "z", "origin": [8, 2.75, 11.75]},
			"faces": {
				"north": {"uv": [5, 6.5, 5.25, 7.5], "texture": "#2"},
				"east": {"uv": [0.75, 6.5, 1.25, 7.5], "texture": "#2"},
				"south": {"uv": [5.25, 7.25, 5.5, 8.25], "texture": "#2"},
				"west": {"uv": [4, 6.5, 4.5, 7.5], "texture": "#2"},
				"up": {"uv": [3.25, 8, 3, 7.5], "texture": "#2"},
				"down": {"uv": [3.5, 7.5, 3.25, 8], "texture": "#2"}
			}
		}
	],
	"display": {
		"thirdperson_righthand": {
			"translation": [0, 6.25, -5.25]
		},
		"thirdperson_lefthand": {
			"translation": [0, 6.25, -5.25]
		},
		"firstperson_righthand": {
			"rotation": [2, -1, 0],
			"translation": [-5.25, 10.25, -3.25]
		},
		"firstperson_lefthand": {
			"rotation": [2, -1, 0],
			"translation": [-5.25, 10.25, -3.25]
		},
		"ground": {
			"translation": [0, 6, 0]
		},
		"gui": {
			"rotation": [25, -152, 4],
			"translation": [1.25, 4.75, 0],
			"scale": [1.17, 1.17, 1.17]
		},
		"fixed": {
			"rotation": [0, 91, 0],
			"translation": [-2, 10, -3.25],
			"scale": [2, 2, 2]
		}
	},
	"groups": [
		{
			"name": "bone",
			"origin": [0, 0, 0],
			"color": 0,
			"children": [
				0,
				1,
				2,
				3,
				4,
				{
					"name": "group",
					"origin": [8, 2.75, 11.75],
					"color": 0,
					"children": [5, 6, 7, 8, 9, 10, 11, 12, 13, 14, 15, 16]
				}
			]
		}
	]
}